<annotation>
	<folder>XML</folder>
	<filename>jaguarundi00000169.jpg</filename>
	<path>/media/usp/DATA/GabrielSFerrante/PROJETO/BRA-Dataset/Dataset/images/jaguarundi/jaguarundi00000169.jpg</path>
	<source>
		<database>Unknown</database>
	</source>
	<size>
		<width>2048</width>
		<height>1289</height>
		<depth>3</depth>
	</size>
	<segmented>0</segmented>
	<object>
		<name>Jaguarundi</name>
		<pose>Unspecified</pose>
		<truncated>0</truncated>
		<difficult>0</difficult>
		<bndbox>
			<xmin>630</xmin>
			<ymin>25</ymin>
			<xmax>1771</xmax>
			<ymax>1150</ymax>
		</bndbox>
	</object>
</annotation>
