<annotation>
	<folder>XML</folder>
	<filename>anta00000022.jpg</filename>
	<path>/media/usp/DATA/GabrielSFerrante/PROJETO/BRA-Dataset/Dataset/imagens-YOLO-rotulation/anta/anta00000022.jpg</path>
	<source>
		<database>Unknown</database>
	</source>
	<size>
		<width>760</width>
		<height>516</height>
		<depth>3</depth>
	</size>
	<segmented>0</segmented>
	<object>
		<name>Anta</name>
		<pose>Unspecified</pose>
		<truncated>0</truncated>
		<difficult>0</difficult>
		<bndbox>
			<xmin>17</xmin>
			<ymin>5</ymin>
			<xmax>583</xmax>
			<ymax>224</ymax>
		</bndbox>
	</object>
	<object>
		<name>Anta</name>
		<pose>Unspecified</pose>
		<truncated>0</truncated>
		<difficult>0</difficult>
		<bndbox>
			<xmin>411</xmin>
			<ymin>122</ymin>
			<xmax>753</xmax>
			<ymax>491</ymax>
		</bndbox>
	</object>
</annotation>
