<annotation>
	<folder>XML</folder>
	<filename>oncaParda00000339.jpg</filename>
	<path>/media/usp/DATA/GabrielSFerrante/PROJETO/BRA-Dataset/Dataset/images/oncaParda/oncaParda00000339.jpg</path>
	<source>
		<database>Unknown</database>
	</source>
	<size>
		<width>800</width>
		<height>765</height>
		<depth>3</depth>
	</size>
	<segmented>0</segmented>
	<object>
		<name>OncaParda</name>
		<pose>Unspecified</pose>
		<truncated>0</truncated>
		<difficult>0</difficult>
		<bndbox>
			<xmin>230</xmin>
			<ymin>427</ymin>
			<xmax>412</xmax>
			<ymax>597</ymax>
		</bndbox>
	</object>
</annotation>
