<annotation>
	<folder>XML</folder>
	<filename>loboGuara00000267.jpg</filename>
	<path>/media/usp/DATA/GabrielSFerrante/PROJETO/BRA-Dataset/Dataset/images/loboGuara/loboGuara00000267.jpg</path>
	<source>
		<database>Unknown</database>
	</source>
	<size>
		<width>660</width>
		<height>330</height>
		<depth>3</depth>
	</size>
	<segmented>0</segmented>
	<object>
		<name>LoboGuara</name>
		<pose>Unspecified</pose>
		<truncated>0</truncated>
		<difficult>0</difficult>
		<bndbox>
			<xmin>220</xmin>
			<ymin>145</ymin>
			<xmax>567</xmax>
			<ymax>315</ymax>
		</bndbox>
	</object>
	<object>
		<name>LoboGuara</name>
		<pose>Unspecified</pose>
		<truncated>0</truncated>
		<difficult>0</difficult>
		<bndbox>
			<xmin>4</xmin>
			<ymin>3</ymin>
			<xmax>432</xmax>
			<ymax>181</ymax>
		</bndbox>
	</object>
</annotation>
