<annotation>
	<folder>XML</folder>
	<filename>loboGuara00000264.jpg</filename>
	<path>/media/usp/DATA/GabrielSFerrante/PROJETO/BRA-Dataset/Dataset/images/loboGuara/loboGuara00000264.jpg</path>
	<source>
		<database>Unknown</database>
	</source>
	<size>
		<width>800</width>
		<height>500</height>
		<depth>3</depth>
	</size>
	<segmented>0</segmented>
	<object>
		<name>LoboGuara</name>
		<pose>Unspecified</pose>
		<truncated>0</truncated>
		<difficult>0</difficult>
		<bndbox>
			<xmin>38</xmin>
			<ymin>14</ymin>
			<xmax>751</xmax>
			<ymax>483</ymax>
		</bndbox>
	</object>
</annotation>
