<annotation>
	<folder>XML</folder>
	<filename>loboGuara00000114.jpg</filename>
	<path>/media/usp/DATA/GabrielSFerrante/PROJETO/BRA-Dataset/Dataset/images/loboGuara/loboGuara00000114.jpg</path>
	<source>
		<database>Unknown</database>
	</source>
	<size>
		<width>560</width>
		<height>393</height>
		<depth>3</depth>
	</size>
	<segmented>0</segmented>
	<object>
		<name>LoboGuara</name>
		<pose>Unspecified</pose>
		<truncated>0</truncated>
		<difficult>0</difficult>
		<bndbox>
			<xmin>89</xmin>
			<ymin>42</ymin>
			<xmax>522</xmax>
			<ymax>342</ymax>
		</bndbox>
	</object>
</annotation>
