<annotation>
	<folder>XML</folder>
	<filename>tamanduaBandeira00000165.jpg</filename>
	<path>/media/usp/DATA/GabrielSFerrante/PROJETO/BRA-Dataset/Dataset/images/tamanduaBandeira/tamanduaBandeira00000165.jpg</path>
	<source>
		<database>Unknown</database>
	</source>
	<size>
		<width>1248</width>
		<height>768</height>
		<depth>3</depth>
	</size>
	<segmented>0</segmented>
	<object>
		<name>TamanduaBandeira</name>
		<pose>Unspecified</pose>
		<truncated>0</truncated>
		<difficult>0</difficult>
		<bndbox>
			<xmin>121</xmin>
			<ymin>219</ymin>
			<xmax>1116</xmax>
			<ymax>647</ymax>
		</bndbox>
	</object>
</annotation>
