<annotation>
	<folder>XML</folder>
	<filename>loboGuara00000148.jpg</filename>
	<path>/media/usp/DATA/GabrielSFerrante/PROJETO/BRA-Dataset/Dataset/images/loboGuara/loboGuara00000148.jpg</path>
	<source>
		<database>Unknown</database>
	</source>
	<size>
		<width>6000</width>
		<height>4000</height>
		<depth>3</depth>
	</size>
	<segmented>0</segmented>
	<object>
		<name>LoboGuara</name>
		<pose>Unspecified</pose>
		<truncated>0</truncated>
		<difficult>0</difficult>
		<bndbox>
			<xmin>514</xmin>
			<ymin>161</ymin>
			<xmax>3937</xmax>
			<ymax>3861</ymax>
		</bndbox>
	</object>
</annotation>
