<annotation>
	<folder></folder>
	<filename>00000000_jpg.rf.b544a0e24e7b539c78cb3a9332817bec.jpg</filename>
	<path>00000000_jpg.rf.b544a0e24e7b539c78cb3a9332817bec.jpg</path>
	<source>
		<database>roboflow.ai</database>
	</source>
	<size>
		<width>984</width>
		<height>554</height>
		<depth>3</depth>
	</size>
	<segmented>0</segmented>
	<object>
		<name>OncaParda</name>
		<pose>Unspecified</pose>
		<truncated>0</truncated>
		<difficult>0</difficult>
		<occluded>0</occluded>
		<bndbox>
			<xmin>30</xmin>
			<xmax>870</xmax>
			<ymin>103</ymin>
			<ymax>515</ymax>
		</bndbox>
	</object>
</annotation>
