<annotation>
	<folder></folder>
	<filename>00000537_jpg.rf.df4166243de4aad1142db4029a00a7d0.jpg</filename>
	<path>00000537_jpg.rf.df4166243de4aad1142db4029a00a7d0.jpg</path>
	<source>
		<database>roboflow.ai</database>
	</source>
	<size>
		<width>3648</width>
		<height>2736</height>
		<depth>3</depth>
	</size>
	<segmented>0</segmented>
	<object>
		<name>Anta</name>
		<pose>Unspecified</pose>
		<truncated>0</truncated>
		<difficult>0</difficult>
		<occluded>0</occluded>
		<bndbox>
			<xmin>158</xmin>
			<xmax>2895</xmax>
			<ymin>1328</ymin>
			<ymax>2396</ymax>
		</bndbox>
	</object>
</annotation>
