<annotation>
	<folder></folder>
	<filename>00000304_jpg.rf.aad9e5d8dceba693e9a990292e07af4e.jpg</filename>
	<path>00000304_jpg.rf.aad9e5d8dceba693e9a990292e07af4e.jpg</path>
	<source>
		<database>roboflow.ai</database>
	</source>
	<size>
		<width>339</width>
		<height>509</height>
		<depth>3</depth>
	</size>
	<segmented>0</segmented>
	<object>
		<name>Jaguarundi</name>
		<pose>Unspecified</pose>
		<truncated>0</truncated>
		<difficult>0</difficult>
		<occluded>0</occluded>
		<bndbox>
			<xmin>9</xmin>
			<xmax>187</xmax>
			<ymin>54</ymin>
			<ymax>352</ymax>
		</bndbox>
	</object>
</annotation>
