<annotation>
	<folder></folder>
	<filename>00000041_jpg.rf.ff58a8438071c452ddc7e9b880130653.jpg</filename>
	<path>00000041_jpg.rf.ff58a8438071c452ddc7e9b880130653.jpg</path>
	<source>
		<database>roboflow.ai</database>
	</source>
	<size>
		<width>865</width>
		<height>500</height>
		<depth>3</depth>
	</size>
	<segmented>0</segmented>
	<object>
		<name>LoboGuara</name>
		<pose>Unspecified</pose>
		<truncated>0</truncated>
		<difficult>0</difficult>
		<occluded>0</occluded>
		<bndbox>
			<xmin>39</xmin>
			<xmax>143</xmax>
			<ymin>249</ymin>
			<ymax>344</ymax>
		</bndbox>
	</object>
	<object>
		<name>LoboGuara</name>
		<pose>Unspecified</pose>
		<truncated>0</truncated>
		<difficult>0</difficult>
		<occluded>0</occluded>
		<bndbox>
			<xmin>371</xmin>
			<xmax>840</xmax>
			<ymin>66</ymin>
			<ymax>468</ymax>
		</bndbox>
	</object>
</annotation>
